terrapyn/__init__.py
terrapyn/conversion.py
terrapyn/dask_utils.py
terrapyn/io.py
terrapyn/logger.py
terrapyn/space.py
terrapyn/stats.py
terrapyn/time.py
terrapyn/utils.py
terrapyn/validation.py
terrapyn/indices/__init__.py
terrapyn/indices/_agro.py
terrapyn/indices/spi.py
terrapyn/params/__init__.py
terrapyn/params/etp.py
terrapyn/params/soil.py
terrapyn/params/solar.py
terrapyn/scoring/__init__.py
terrapyn/scoring/_contingency.py
terrapyn/scoring/_scoring.py
terrapyn/scoring/metrics.py
terrapyn-0.3.1.dist-info/METADATA
terrapyn-0.3.1.dist-info/WHEEL
terrapyn-0.3.1.dist-info/licenses/AUTHORS.md
terrapyn-0.3.1.dist-info/licenses/LICENSE.md
terrapyn-0.3.1.dist-info/RECORD
