Metadata-Version: 2.4
Name: terrapyn
Version: 0.3.1
Summary: Toolkit to manipulate Earth observations and models.
Author-email: Colin Hill <colinalastairhill@gmail.com>
License: BSD License
License-File: AUTHORS.md
License-File: LICENSE.md
Classifier: Development Status :: 5 - Production/Stable
Classifier: Intended Audience :: Developers
Classifier: License :: OSI Approved :: BSD License
Classifier: Programming Language :: Python :: 3.10
Classifier: Programming Language :: Python :: 3.11
Classifier: Programming Language :: Python :: 3.12
Classifier: Programming Language :: Python :: 3.13
Requires-Python: >=3.10
Requires-Dist: bokeh>=3.7.3
Requires-Dist: bottleneck>=1.5.0
Requires-Dist: dask>=2025.7.0
Requires-Dist: distributed>=2025.7.0
Requires-Dist: fiona>=1.10.1
Requires-Dist: gcsfs>=2025.7.0
Requires-Dist: geopandas>=1.1.1
Requires-Dist: ipykernel>=6.30.1
Requires-Dist: jupyterlab>=4.4.6
Requires-Dist: matplotlib>=3.10.5
Requires-Dist: netcdf4>=1.7.2
Requires-Dist: numpy>=2.2.6
Requires-Dist: odc-geo>=0.4.10
Requires-Dist: openpyxl>=3.1.5
Requires-Dist: pandas>=2.3.1
Requires-Dist: pyarrow>=21.0.0
Requires-Dist: rioxarray>=0.19.0
Requires-Dist: scikit-learn>=1.7.1
Requires-Dist: scipy>=1.15.3
Requires-Dist: seaborn>=0.13.2
Requires-Dist: shapely>=2.1.1
Requires-Dist: tqdm>=4.67.1
Requires-Dist: xarray>=2025.6.1
Requires-Dist: zarr>=2.18.3
